tentypy/__init__.py
tentypy/config.py
tentypy/builder/__init__.py
tentypy/builder/cli.py
tentypy/builder/config.py
tentypy/builder/core/__init__.py
tentypy/builder/core/file_generator.py
tentypy/builder/core/template_engine.py
tentypy/builder/core/validator.py
tentypy/builder/templates/__init__.py
tentypy/builder/templates/clean_architecture.json
tentypy/builder/templates/django_ddd.yaml
tentypy/builder/templates/fastapi_basic.json
tentypy/builder/templates/microservices.yaml
tentypy/utils/__init__.py
tentypy/utils/logger.py
tentypy_builder-1.0.0.dist-info/licenses/LICENSE
tentypy_builder-1.0.0.dist-info/METADATA
tentypy_builder-1.0.0.dist-info/WHEEL
tentypy_builder-1.0.0.dist-info/entry_points.txt
tentypy_builder-1.0.0.dist-info/top_level.txt
tentypy_builder-1.0.0.dist-info/RECORD
