Metadata-Version: 2.4
Name: tentypy-builder
Version: 1.0.0
Summary: Professional project structure generator with JSON and YAML template support
Home-page: https://github.com/Keniding/tentypy-builder
Author: Keniding
Author-email: Keniding <kenidingh@gmail.com>
License: MIT
Project-URL: Homepage, https://github.com/keniding/tentypy-builder
Project-URL: Repository, https://github.com/keniding/tentypy-builder
Project-URL: Issues, https://github.com/keniding/tentypy-builder/issues
Project-URL: Documentation, https://github.com/keniding/tentypy-builder#readme
Keywords: project-generator,template,builder,architecture,clean-architecture,ddd,microservices,fastapi,django
Classifier: Development Status :: 4 - Beta
Classifier: Intended Audience :: Developers
Classifier: Topic :: Software Development :: Code Generators
Classifier: Topic :: Software Development :: Libraries :: Python Modules
Classifier: License :: OSI Approved :: MIT License
Classifier: Programming Language :: Python :: 3
Classifier: Programming Language :: Python :: 3.9
Classifier: Programming Language :: Python :: 3.10
Classifier: Programming Language :: Python :: 3.11
Classifier: Programming Language :: Python :: 3.12
Classifier: Operating System :: OS Independent
Requires-Python: >=3.8
License-File: LICENSE
Requires-Dist: rich>=13.7.0
Requires-Dist: click>=8.1.7
Provides-Extra: yaml
Requires-Dist: pyyaml>=6.0.1; extra == "yaml"
Provides-Extra: interactive
Requires-Dist: inquirer>=3.1.3; extra == "interactive"
Provides-Extra: dev
Requires-Dist: pytest>=7.4.0; extra == "dev"
Requires-Dist: pytest-cov>=4.1.0; extra == "dev"
Requires-Dist: black>=23.7.0; extra == "dev"
Requires-Dist: flake8>=6.1.0; extra == "dev"
Requires-Dist: isort>=5.13.0; extra == "dev"
Requires-Dist: mypy>=1.5.0; extra == "dev"
Requires-Dist: types-PyYAML>=6.0.12; extra == "dev"
Requires-Dist: pre-commit>=3.5.0; extra == "dev"
Requires-Dist: build>=0.10.0; extra == "dev"
Requires-Dist: twine>=4.0.2; extra == "dev"
Provides-Extra: all
Requires-Dist: pyyaml>=6.0.1; extra == "all"
Requires-Dist: inquirer>=3.1.3; extra == "all"
Dynamic: author
Dynamic: home-page
Dynamic: license-file
Dynamic: requires-python
